gstripe/__init__.py
gstripe/datasources.py
gstripe/genomic_tools.py
gstripe/graphs.py
gstripe/gstripe.py
gstripe/ranges.py
gstripe/stats.py
gstripe/task.py
gstripe/utils.py
gstripe-1.0.0.dist-info/licenses/LICENSE.txt
gstripe-1.0.0.dist-info/METADATA
gstripe-1.0.0.dist-info/WHEEL
gstripe-1.0.0.dist-info/top_level.txt
gstripe-1.0.0.dist-info/RECORD
