Metadata-Version: 2.4
Name: gstripe
Version: 1.0.0
Summary: Graph-based stripe caller using chromain interaction data.
Author-email: Michał Denkiewicz <michal.denkiewicz@datascience.edu.pl>
License: MIT License
Keywords: stripes,genomics,bioinformatics
Classifier: Programming Language :: Python
Classifier: Programming Language :: Python :: 3
Classifier: License :: OSI Approved :: MIT License
Requires-Python: >=3.10
License-File: LICENSE.txt
Requires-Dist: numpy>=2.0.0
Requires-Dist: pandas>=2.2.2
Requires-Dist: scipy>=1.13.1
Requires-Dist: igraph>=0.11.5
Requires-Dist: matplotlib>=3.9.0
Requires-Dist: setuptools>=70.1.0
Requires-Dist: seaborn>=0.13.2
Provides-Extra: test
Requires-Dist: pytest; extra == "test"
Provides-Extra: stats
Requires-Dist: hic-straw>=1.3.1; extra == "stats"
Dynamic: license-file
